[
    {
        "name": "Mary Lee",
        "weight": "81",
        "height": "177"
    },
    {
        "name": "John Kwan",
        "weight": "59",
        "height": "181"
    },
    {
        "name": "Donald Trump",
        "weight": "83",
        "height": "188"
    },
    {
        "name": "Carrot",
        "weight": "57",
        "height": "179"
    },
    {
        "name": "Potato",
        "weight": "75",
        "height": "179"
    },
    {
        "name": "Cayo",
        "weight": "100",
        "height": "179"
    },
    {
        "name": "Joe Biden",
        "weight": "92",
        "height": "197"
    },
    {
        "name": "Obama",
        "weight": "58",
        "height": "181"
    },
    {
        "name": "Jacky Chan",
        "weight": "85",
        "height": "169"
    },
    {
        "name": "Tomato",
        "weight": "83",
        "height": "168"
    },
    {
        "name": "Onion",
        "weight": "68",
        "height": "197"
    },
    {
        "name": "Rachel",
        "weight": "68",
        "height": "173"
    }
]
